rmout/__init__.py
rmout/core.py
rmout/files.py
rmout/trash.py
rmout-0.3.0.dist-info/LICENCE.md
rmout-0.3.0.dist-info/METADATA
rmout-0.3.0.dist-info/WHEEL
rmout-0.3.0.dist-info/entry_points.txt
rmout-0.3.0.dist-info/top_level.txt
rmout-0.3.0.dist-info/RECORD
