Metadata-Version: 2.1
Name: rmout
Version: 0.3.0
Summary: rmout is a tool for throwing unnecessary files in a directory into the trash.
Home-page: https://github.com/simulation-lab/rmout
Author: kino
Author-email: simulation.space.labs@gmail.com
License: UNKNOWN
Platform: UNKNOWN
Classifier: License :: OSI Approved :: MIT License
Classifier: Programming Language :: Python :: 3
Classifier: Programming Language :: Python :: 3.8
Classifier: Programming Language :: Python :: 3.9
Classifier: Programming Language :: Python :: 3.10
Classifier: Operating System :: OS Independent
Requires-Python: ~=3.8
License-File: LICENCE.md
Requires-Dist: click (~=7.1)
Requires-Dist: send2trash (~=1.5)
